odoo8_addon_mrp_repair_layout-8.0.1.0.0.99.dev3-py2.7-nspkg.pth
odoo8_addon_mrp_repair_layout-8.0.1.0.0.99.dev3.dist-info/METADATA
odoo8_addon_mrp_repair_layout-8.0.1.0.0.99.dev3.dist-info/RECORD
odoo8_addon_mrp_repair_layout-8.0.1.0.0.99.dev3.dist-info/WHEEL
odoo8_addon_mrp_repair_layout-8.0.1.0.0.99.dev3.dist-info/namespace_packages.txt
odoo8_addon_mrp_repair_layout-8.0.1.0.0.99.dev3.dist-info/top_level.txt
odoo_addons/mrp_repair_layout/README.rst
odoo_addons/mrp_repair_layout/__init__.py
odoo_addons/mrp_repair_layout/__openerp__.py
odoo_addons/mrp_repair_layout/i18n/sl.po
odoo_addons/mrp_repair_layout/models/__init__.py
odoo_addons/mrp_repair_layout/models/mrp_repair.py
odoo_addons/mrp_repair_layout/models/mrp_repair_layout_category.py
odoo_addons/mrp_repair_layout/security/ir.model.access.csv
odoo_addons/mrp_repair_layout/static/description/icon.png
odoo_addons/mrp_repair_layout/views/layout_templates.xml
odoo_addons/mrp_repair_layout/views/mrp_repair_layout_category_view.xml
odoo_addons/mrp_repair_layout/views/mrp_repair_layouted.xml
odoo_addons/mrp_repair_layout/views/mrp_repair_view.xml
